alloy_config_generator/__init__.py
alloy_config_generator/__main__.py
alloy_config_generator/cli.py
alloy_config_generator/templates/argocd.application.j2
alloy_config_generator/templates/config.alloy.j2
alloy_config_generator-0.1.3.dist-info/METADATA
alloy_config_generator-0.1.3.dist-info/WHEEL
alloy_config_generator-0.1.3.dist-info/entry_points.txt
alloy_config_generator-0.1.3.dist-info/RECORD
