Metadata-Version: 2.4
Name: alloy-config-generator
Version: 0.1.3
Summary: Deterministic Grafana Alloy configuration generator.
Requires-Python: >=3.9
Requires-Dist: jinja2>=3.1
Requires-Dist: pyyaml>=6.0
Provides-Extra: dev
Requires-Dist: pytest>=7.4; extra == 'dev'
